panopta_api/__init__.py
panopta_api/client.py
panopta_api-2.0.0.dist-info/WHEEL
panopta_api-2.0.0.dist-info/DESCRIPTION.rst
panopta_api-2.0.0.dist-info/metadata.json
panopta_api-2.0.0.dist-info/RECORD
panopta_api-2.0.0.dist-info/METADATA
panopta_api-2.0.0.dist-info/top_level.txt
