Metadata-Version: 2.0
Name: panopta-api
Version: 2.0.0
Summary: Panopta API Client
Home-page: https://github.com/Panopta/python-panopta-api-client
Author: Panopta
Author-email: support@panopta.com
License: MIT
Platform: UNKNOWN
Requires-Dist: requests
Requires-Dist: requests-toolbelt
